lotus/__init__.py
lotus/client.py
lotus/consumer.py
lotus/models.py
lotus/request.py
lotus/utils.py
lotus/version.py
lotus/tests/__init__.py
lotus/tests/test_e2e.py
lotus_python-0.12.0.dist-info/LICENSE
lotus_python-0.12.0.dist-info/METADATA
lotus_python-0.12.0.dist-info/WHEEL
lotus_python-0.12.0.dist-info/top_level.txt
lotus_python-0.12.0.dist-info/RECORD
