Metadata-Version: 2.1
Name: lotus-python
Version: 0.12.0
Summary: Integrate Lotus into any python application.
Home-page: https://github.com/uselotus/lotus-python
Author: Lotus
Author-email: founders@lotus.io
Maintainer: Lotus
Maintainer-email: founders@lotus.io
License: MIT License
Classifier: Development Status :: 5 - Production/Stable
Classifier: Intended Audience :: Developers
Classifier: License :: OSI Approved :: MIT License
Classifier: Operating System :: OS Independent
Classifier: Programming Language :: Python
Classifier: Programming Language :: Python :: 3
Classifier: Programming Language :: Python :: 3.2
Classifier: Programming Language :: Python :: 3.3
Classifier: Programming Language :: Python :: 3.4
Classifier: Programming Language :: Python :: 3.5
Classifier: Programming Language :: Python :: 3.6
Classifier: Programming Language :: Python :: 3.7
Classifier: Programming Language :: Python :: 3.8
License-File: LICENSE
Requires-Dist: requests (<3.0,>=2.7)
Requires-Dist: six (>=1.5)
Requires-Dist: monotonic (>=1.5)
Requires-Dist: backoff (>=1.6.0)
Requires-Dist: python-dateutil (>2.1)
Requires-Dist: pydantic[email] (>=1.10.0)
